cjen/__init__.py
cjen/bigtangerine.py
cjen/commons.py
cjen/context.py
cjen/db_bigtangerine.py
cjen/exceptions.py
cjen/aiai/__init__.py
cjen/aiai/context.py
cjen/aiai/file-content-type.yaml
cjen/aiai/headers.py
cjen/aiai/http.py
cjen/aiai/jwt.py
cjen/dada/__init__.py
cjen/dada/smile.py
cjen/mama/__init__.py
cjen/mama/meta_data.py
cjen/mama/operate/__init__.py
cjen/mama/operate/asserts.py
cjen/mama/operate/common.py
cjen/mama/operate/json.py
cjen/mama/operate/mysql.py
cjen/mama/operate/xlsx.py
cjen/nene/__init__.py
cjen/nene/caculate_utils.py
cjen/nene/collection_utils.py
cjen/nene/database_info.py
cjen/nene/database_pool.py
cjen/nene/helper.py
cjen/nene/properties.py
cjen/nene/time_utils.py
cjen/nene/collections/__init__.py
cjen/nene/collections/node.py
cjen/nene/collections/tree.py
cjen/sco/__init__.py
cjen/sco/scenario.py
cjen/sco/standard_step.py
cjen/sco/step.py
cjen/sco/step_definitions.py
cjen/tests/__init__.py
cjen/tests/main_app.py
cjen/tests/mock_service.py
cjen/tests/test_tree.py
cjen/tests/tests_property.py
cjen/tests/aiai/__init__.py
cjen/tests/aiai/conftest.py
cjen/tests/aiai/test_header.py
cjen/tests/aiai/test_http.py
cjen/tests/aiai/test_jwt.py
cjen/tests/common/__init__.py
cjen/tests/common/test_common_value.py
cjen/tests/common/test_context_manager.py
cjen/tests/dada/__init__.py
cjen/tests/dada/test_delay.py
cjen/tests/dada/test_smile_parallel1.py
cjen/tests/dada/test_smile_parallel2.py
cjen/tests/step/__init__.py
cjen/tests/step/conftest.py
cjen/tests/step/ok_response.py
cjen/tests/step/ok_step.py
cjen/tests/step/other_step.py
cjen/tests/step/test_step.py
cjen-1.0.18.dist-info/LICENSE
cjen-1.0.18.dist-info/METADATA
cjen-1.0.18.dist-info/WHEEL
cjen-1.0.18.dist-info/top_level.txt
cjen-1.0.18.dist-info/RECORD
