Metadata-Version: 2.1
Name: cjen
Version: 1.0.18
Summary: automation test helper
Home-page: https://github.com/thcpc/cjen
Author: thcpc
Author-email: redcpc@163.com
Project-URL: Bug Tracker, https://github.com/thcpc/cjen/issues
Classifier: Programming Language :: Python :: 3
Classifier: License :: OSI Approved :: MIT License
Classifier: Operating System :: OS Independent
Requires-Python: >=3.9
License-File: LICENSE
Requires-Dist: docx
Requires-Dist: jsonpath
Requires-Dist: PyMySQL
Requires-Dist: pytest
Requires-Dist: PyYAML
Requires-Dist: requests
Requires-Dist: requests-toolbelt
Requires-Dist: ruamel.yaml
Requires-Dist: ruamel.yaml.clib
Requires-Dist: DBUtils
Requires-Dist: chardet
Requires-Dist: openpyxl
